FastOMA/__init__.py
FastOMA/_hog_class.py
FastOMA/_infer_subhog.py
FastOMA/_utils_frag_SO_detection.py
FastOMA/_utils_roothog.py
FastOMA/_utils_subhog.py
FastOMA/_wrappers.py
FastOMA/batch_roothogs.py
FastOMA/check_input.py
FastOMA/collect_subhogs.py
FastOMA/fastoma_notebook_stat.ipynb
FastOMA/helper_scripts.py
FastOMA/infer_roothogs.py
FastOMA/infer_subhogs.py
FastOMA/logging_setup.py
FastOMA/transformer.py
FastOMA/zoo/README.md
FastOMA/zoo/__init__.py
FastOMA/zoo/unionfind.py
FastOMA/zoo/utils.py
FastOMA/zoo/familyanalyzer/__init__.py
FastOMA/zoo/familyanalyzer/genetree.py
FastOMA/zoo/familyanalyzer/newick.py
FastOMA/zoo/familyanalyzer/orthoxmlquery.py
FastOMA/zoo/familyanalyzer/taxonomy.py
FastOMA/zoo/familyanalyzer/tools.py
FastOMA/zoo/file_utils/__init__.py
FastOMA/zoo/file_utils/context_managers.py
FastOMA/zoo/file_utils/extractors.py
FastOMA/zoo/hog/__init__.py
FastOMA/zoo/hog/convert.py
FastOMA/zoo/hog/extract_groups.py
FastOMA/zoo/hog/extract_hog_info.py
FastOMA/zoo/hog/filter_orthoxml.py
FastOMA/zoo/hog/orthoxml_merge.py
FastOMA/zoo/hog/transform.py
FastOMA/zoo/seq_utils/__init__.py
FastOMA/zoo/seq_utils/utils.py
FastOMA/zoo/wrappers/__init__.py
FastOMA/zoo/wrappers/abstract_cli.py
FastOMA/zoo/wrappers/options.py
FastOMA/zoo/wrappers/aligners/__init__.py
FastOMA/zoo/wrappers/aligners/base_aligner.py
FastOMA/zoo/wrappers/aligners/mafft.py
FastOMA/zoo/wrappers/aligners/muscle.py
FastOMA/zoo/wrappers/aligners/probcons.py
FastOMA/zoo/wrappers/aligners/prographmsa.py
FastOMA/zoo/wrappers/modeltesters/__init__.py
FastOMA/zoo/wrappers/modeltesters/base_modeltester.py
FastOMA/zoo/wrappers/modeltesters/parsers.py
FastOMA/zoo/wrappers/modeltesters/prottest.py
FastOMA/zoo/wrappers/treebuilders/__init__.py
FastOMA/zoo/wrappers/treebuilders/base_treebuilder.py
FastOMA/zoo/wrappers/treebuilders/fasttree.py
FastOMA/zoo/wrappers/treebuilders/guenomu.py
FastOMA/zoo/wrappers/treebuilders/iqtree.py
FastOMA/zoo/wrappers/treebuilders/parsers.py
fastoma-0.5.1.dist-info/METADATA
fastoma-0.5.1.dist-info/WHEEL
fastoma-0.5.1.dist-info/entry_points.txt
fastoma-0.5.1.dist-info/RECORD
