Metadata-Version: 2.4
Name: FastOMA
Version: 0.5.1
Summary: FastOMA - a package to infer orthology information among proteomes
Project-URL: Homepage, https://github.com/DessimozLab/FastOMA
Author-email: Sina Majidian <sina.majidian@gmail.com>, Adrian Altenhoff <adrian.altenhoff@inf.ethz.ch>
License-Expression: MIT
Requires-Python: <3.13,>=3.8
Requires-Dist: biopython~=1.81
Requires-Dist: dendropy<=4.6.1,>=4.5
Requires-Dist: ete3~=3.1
Requires-Dist: lxml<6,>=4.6
Requires-Dist: networkx
Requires-Dist: numpy
Requires-Dist: omamer!=2.1.1,<3,>=2.1
Requires-Dist: pyham~=1.1
Requires-Dist: pyparsing
Provides-Extra: nextflow
Requires-Dist: nextflow; extra == 'nextflow'
Provides-Extra: report
Requires-Dist: jupyter; extra == 'report'
Requires-Dist: matplotlib; extra == 'report'
Requires-Dist: papermill; extra == 'report'
Requires-Dist: seaborn; extra == 'report'
